transtex/__init__.py
transtex/bibtex.py
transtex/converter.py
transtex/formatting.py
transtex/parsing.py
transtex/reference.py
transtex/__pycache__/__init__.cpython-312.pyc
transtex/__pycache__/bibtex.cpython-312.pyc
transtex/__pycache__/converter.cpython-312.pyc
transtex/__pycache__/formatting.cpython-312.pyc
transtex/__pycache__/parsing.cpython-312.pyc
transtex/__pycache__/reference.cpython-312.pyc
transtex/formatters/__init__.py
transtex/formatters/apa6.py
transtex/formatters/apa7.py
transtex/formatters/chicago.py
transtex/formatters/ieee.py
transtex/formatters/mla.py
transtex/formatters/shared.py
transtex/formatters/vancouver.py
transtex/formatters/__pycache__/__init__.cpython-312.pyc
transtex/formatters/__pycache__/apa.cpython-312.pyc
transtex/formatters/__pycache__/apa6.cpython-312.pyc
transtex/formatters/__pycache__/apa7.cpython-312.pyc
transtex/formatters/__pycache__/chicago.cpython-312.pyc
transtex/formatters/__pycache__/ieee.cpython-312.pyc
transtex/formatters/__pycache__/mla.cpython-312.pyc
transtex/formatters/__pycache__/shared.cpython-312.pyc
transtex/formatters/__pycache__/vancouver.cpython-312.pyc
transtex/parsers/__init__.py
transtex/parsers/apa.py
transtex/parsers/chicago.py
transtex/parsers/ieee.py
transtex/parsers/mla.py
transtex/parsers/shared.py
transtex/parsers/vancouver.py
transtex/parsers/__pycache__/__init__.cpython-312.pyc
transtex/parsers/__pycache__/apa.cpython-312.pyc
transtex/parsers/__pycache__/chicago.cpython-312.pyc
transtex/parsers/__pycache__/common.cpython-312.pyc
transtex/parsers/__pycache__/ieee.cpython-312.pyc
transtex/parsers/__pycache__/mla.cpython-312.pyc
transtex/parsers/__pycache__/shared.cpython-312.pyc
transtex/parsers/__pycache__/vancouver.cpython-312.pyc
transtex-1.0.2.dist-info/METADATA
transtex-1.0.2.dist-info/WHEEL
transtex-1.0.2.dist-info/top_level.txt
transtex-1.0.2.dist-info/RECORD
