Metadata-Version: 2.4
Name: transtex
Version: 1.0.2
Summary: This library supports bidirectional conversion between APA 6th, IEEE, and other paper reference formats and BibTeX.
Requires-Python: >=3.12
Requires-Dist: setuptools>=80.9.0
Dynamic: requires-python
